{
    "display": {
        "icon": {
            "item": "minecraft:diamond"
        },
        "title": "Алмазы!",
        "description": "Добудь алмазы без читов"
    },
    "parent": "blazeandcave:mining/isnt_it_iron_pick",
    "rewards": {
		"function": "bc_rewards:mining/diamonds"
    },			
    "criteria": {
        "diamond": {
            "trigger": "minecraft:inventory_changed",
            "conditions": {
                "items": [
                    {
                        "item": "minecraft:diamond"
                    }
                ]
            }
        }
    }
}