{
    "display": {
        "icon": {
            "item": "minecraft:armor_stand"
        },
        "title": "Манекен",
        "description": "Скрафти стойку для брони"
    },
    "parent": "blazeandcave:building/a_masterpiece",
	"rewards": {
		"function": "bc_rewards:building/mannequin"
    },		
    "criteria": {
        "armor_stand": {
            "trigger": "minecraft:inventory_changed",
            "conditions": {
                "items": [
                    {
                        "item": "minecraft:armor_stand"
                    }
                ]
            }
        }
    }
}