{
    "display": {
        "icon": {
            "item": "minecraft:stone_pressure_plate"
        },
        "title": "Под давлением",
        "description": "Скрафтите нажимную плиту"
    },
    "parent": "blazeandcave:redstone/root",
	"rewards": {
		"function": "bc_rewards:redstone/under_pressure"
    },
    "criteria": {
        "stone": {
            "trigger": "minecraft:inventory_changed",
            "conditions": {
                "items": [
                    {
                        "item": "minecraft:stone_pressure_plate"
                    }
                ]
            }
        },
        "wood": {
            "trigger": "minecraft:inventory_changed",
            "conditions": {
                "items": [
                    {
                        "item": "minecraft:wooden_pressure_plate"
                    }
                ]
            }
        }
    },
    "requirements": [
		[
			"stone", 
			"wood"
		]
	]
}