{
    "display": {
        "icon": {
            "item": "minecraft:iron_boots"
        },
        "title": "Как кошка",
        "description": "Получи ботинки с падением пера",
		"frame": "goal"
    },
    "parent": "blazeandcave:enchanting/root",
    "rewards": {
		"function": "bc_rewards:enchanting/like_a_cat"
    },			
    "criteria": {
        "feather_falling": {
            "trigger": "minecraft:inventory_changed",
            "conditions": {
				"items": [
					{
						"enchantments": [
							{
								"enchantment": "minecraft:feather_falling"
							}
						]
					}
				]
			}
		}
    }
}