{
    "display": {
        "icon": {
            "item": "minecraft:enchanting_table"
        },
        "title": "Enchanting",
        "description": "Enchant items to give them magical abilities",
		"background": "minecraft:textures/blocks/obsidian.png",
        "show_toast": false,
        "announce_to_chat": false
    },
    "rewards": {
		"function": "bc_rewards:enchanting/root"
    },			
    "criteria": {
        "enchanted_item": {
            "trigger": "minecraft:enchanted_item"
        }
    }
}